direct_redis_new/__init__.py
direct_redis_new/direct_redis.py
direct_redis_new/functions.py
direct_redis_new-0.2.4.2.dist-info/LICENSE
direct_redis_new-0.2.4.2.dist-info/METADATA
direct_redis_new-0.2.4.2.dist-info/WHEEL
direct_redis_new-0.2.4.2.dist-info/top_level.txt
direct_redis_new-0.2.4.2.dist-info/RECORD
