Metadata-Version: 2.1
Name: direct-redis-new
Version: 0.2.4.2
Summary: Serialize any python datatypes and does redis actions using redis-py
Home-page: https://github.com/pypa/sampleproject
Author: YongJe Lee
Author-email: yjlee8510@gmail.com
License: UNKNOWN
Platform: UNKNOWN
Classifier: Programming Language :: Python :: 3
Classifier: License :: OSI Approved :: MIT License
Classifier: Operating System :: OS Independent
Requires-Python: >=3.6
